{"cameraMode":{"drawMode":0,"name":"Shaded","section":"Shading Mode"},"sceneLighting":true,"audioPlay":false,"sceneViewState":{"showFog":true,"showMaterialUpdate":false,"showSkybox":true,"showFlares":true,"showImageEffects":true,"showParticleSystems":true,"showVisualEffectGraphs":true,"m_FxEnabled":true},"in2DMode":false,"pivot":{"x":-3.8743019104003908e-7,"y":0.8618142008781433,"z":2.246988296508789},"rotation":{"x":0.23742657899856568,"y":-0.6256401538848877,"z":0.20823954045772553,"w":0.7133252620697022},"size":9.056390762329102,"orthographic":false}